minesweeper_model/__init__.py
minesweeper_model/field.py
minesweeper_model/generator.py
minesweeper_model/utility.py
minesweeper_model-0.0.2.dist-info/LICENSE
minesweeper_model-0.0.2.dist-info/METADATA
minesweeper_model-0.0.2.dist-info/WHEEL
minesweeper_model-0.0.2.dist-info/top_level.txt
minesweeper_model-0.0.2.dist-info/RECORD
