Metadata-Version: 2.1
Name: minesweeper-model
Version: 0.0.2
Summary: Tools to model a Minesweeper game and interact with it programmatically.
Home-page: https://github.com/ilkutkutlar/minesweeper_model
Author: Ilkut Kutlar
Author-email: ilkutkutlar@gmail.com
License: MIT
Download-URL: https://github.com/ilkutkutlar/minesweeper_model/archive/v0.0.2.tar.gz
Keywords: minesweeper,model
Platform: UNKNOWN
Classifier: Development Status :: 3 - Alpha
Classifier: Intended Audience :: Developers
Classifier: License :: OSI Approved :: MIT License
Classifier: Programming Language :: Python :: 3
Classifier: Programming Language :: Python :: 3.6
